MANIFEST.in
README.rst
pyproject.toml
requirements.txt
setup.cfg
setup.py
t_desktop/__init__.py
t_desktop/config.py
t_desktop/decorators.py
t_desktop/exceptions.py
t_desktop/t_desktop.py
t_desktop.egg-info/PKG-INFO
t_desktop.egg-info/SOURCES.txt
t_desktop.egg-info/dependency_links.txt
t_desktop.egg-info/not-zip-safe
t_desktop.egg-info/requires.txt
t_desktop.egg-info/top_level.txt
t_desktop/monitor/__init__.py
t_desktop/monitor/server_monitor.py
t_desktop/monitor/workitems.py
t_desktop/monitor/assets/Template.xlsx
t_desktop/monitor/assets/__init__.py
t_desktop/monitor/managers/__init__.py
t_desktop/monitor/managers/cpu_manager.py
t_desktop/monitor/managers/disk_manager.py
t_desktop/monitor/managers/memory_manager.py
t_desktop/monitor/spreadhseet/__init__.py
t_desktop/monitor/spreadhseet/g_sheets.py
t_desktop/utils/__init__.py
t_desktop/utils/capture_screenshot.py
t_desktop/utils/logger.py