Metadata-Version: 2.4
Name: t_desktop
Version: 0.1.1
Summary: t-desktop is a Python library that provides common methods for desktop automation, simplifyingtasks like window management, keyboard, and mouse control.
Home-page: https://www.thoughtful.ai/
Author: Thoughtful
Author-email: support@thoughtful.ai
Keywords: t_desktop
Classifier: Intended Audience :: Developers
Classifier: Natural Language :: English
Classifier: Programming Language :: Python :: 3
Classifier: Programming Language :: Python :: 3.9
Requires-Python: >=3.9
Requires-Dist: t-bug-catcher>=0.5.7
Requires-Dist: rpaframework>=28.1.0
Requires-Dist: comtypes<2.0,>=1.2
Requires-Dist: Pillow<11.0,>=10.0
Requires-Dist: pywin32>=306; platform_system == "Windows"
Requires-Dist: pywinauto<1.0,>=0.6; platform_system == "Windows"
Requires-Dist: gspread==6.1.2
Requires-Dist: google-auth==2.32.0
Requires-Dist: twine==1.14.0
Requires-Dist: build==0.3.1.post1
Dynamic: author
Dynamic: author-email
Dynamic: classifier
Dynamic: description
Dynamic: description-content-type
Dynamic: home-page
Dynamic: keywords
Dynamic: requires-dist
Dynamic: requires-python
Dynamic: summary
